fastgs/__init__.py
fastgs/_modidx.py
fastgs/multispectral.py
fastgs/test/__init__.py
fastgs/test/fixture.py
fastgs/test/io.py
fastgs/vision/__init__.py
fastgs/vision/augment.py
fastgs/vision/core.py
fastgs/vision/data.py
fastgs/vision/learner.py
fastgs/vision/load.py
fastgs-0.1.1.dist-info/LICENSE
fastgs-0.1.1.dist-info/METADATA
fastgs-0.1.1.dist-info/WHEEL
fastgs-0.1.1.dist-info/entry_points.txt
fastgs-0.1.1.dist-info/top_level.txt
fastgs-0.1.1.dist-info/RECORD
