Metadata-Version: 2.1
Name: fastgs
Version: 0.1.1
Summary: Geospatial (Sentinel2 Multi-Spectral) support for fastai
Home-page: https://github.com/restlessronin/fastgs
Author: restlessronin
Author-email: 88921269+restlessronin@users.noreply.github.com
License: Apache Software License 2.0
Keywords: geospatial multi-spectral sentinel2 fastai nbdev jupyter notebook python
Classifier: Development Status :: 3 - Alpha
Classifier: Intended Audience :: Developers
Classifier: Natural Language :: English
Classifier: Programming Language :: Python :: 3.7
Classifier: Programming Language :: Python :: 3.8
Classifier: Programming Language :: Python :: 3.9
Classifier: Programming Language :: Python :: 3.10
Classifier: License :: OSI Approved :: Apache Software License
Requires-Python: >=3.7
License-File: LICENSE
Requires-Dist: fastai (>=2.7.10)
Provides-Extra: dev
Requires-Dist: albumentations ; extra == 'dev'
Requires-Dist: ffmpeg ; extra == 'dev'
